Metadata-Version: 1.0
Name: Basic-vector-operations
Version: 0.3
Summary: Basic vector operations such as norm and sum
Home-page: UNKNOWN
Author: UNKNOWN
Author-email: UNKNOWN
License: UNKNOWN
Platform: UNKNOWN
